tests/__init__.py
tests/test_generator.py
PyModuleG-0.1.1.dist-info/LICENSE
PyModuleG-0.1.1.dist-info/METADATA
PyModuleG-0.1.1.dist-info/WHEEL
PyModuleG-0.1.1.dist-info/entry_points.txt
PyModuleG-0.1.1.dist-info/top_level.txt
PyModuleG-0.1.1.dist-info/RECORD
